CHANGES.rst
CONTRIBUTORS.rst
MANIFEST.in
README.rst
buildout.cfg
setup.py
travis.cfg
docs/LICENSE.GPL
docs/LICENSE.rst
docs/index.rst
src/c2/__init__.py
src/c2.patch.sharesettingcopy.egg-info/PKG-INFO
src/c2.patch.sharesettingcopy.egg-info/SOURCES.txt
src/c2.patch.sharesettingcopy.egg-info/dependency_links.txt
src/c2.patch.sharesettingcopy.egg-info/entry_points.txt
src/c2.patch.sharesettingcopy.egg-info/namespace_packages.txt
src/c2.patch.sharesettingcopy.egg-info/not-zip-safe
src/c2.patch.sharesettingcopy.egg-info/requires.txt
src/c2.patch.sharesettingcopy.egg-info/top_level.txt
src/c2/patch/__init__.py
src/c2/patch/sharesettingcopy/__init__.py
src/c2/patch/sharesettingcopy/configure.zcml
src/c2/patch/sharesettingcopy/event.py
src/c2/patch/sharesettingcopy/testing.py
src/c2/patch/sharesettingcopy/controlpanel/__init__.py
src/c2/patch/sharesettingcopy/controlpanel/configure.zcml
src/c2/patch/sharesettingcopy/controlpanel/interfaces.py
src/c2/patch/sharesettingcopy/controlpanel/main.py
src/c2/patch/sharesettingcopy/locales/c2.patch.sharesettingcopy.pot
src/c2/patch/sharesettingcopy/locales/update.sh
src/c2/patch/sharesettingcopy/profiles/default/controlpanel.xml
src/c2/patch/sharesettingcopy/profiles/default/metadata.xml
src/c2/patch/sharesettingcopy/profiles/default/registry.xml
src/c2/patch/sharesettingcopy/tests/__init__.py
src/c2/patch/sharesettingcopy/tests/test_robot.py
src/c2/patch/sharesettingcopy/tests/test_setup.py
src/c2/patch/sharesettingcopy/tests/robot/test_example.robot