Metadata-Version: 1.1
Name: c2.patch.sharesettingcopy
Version: 1.0a3
Summary: This prooduct is take the share setting over from copy objcet at pasting object for Plone.
Home-page: http://pypi.python.org/pypi/c2.patch.sharesettingcopy
Author: Manabu TERADA
Author-email: terada@cmscom.jp
License: GPL version 2
Keywords: Python Plone
Platform: UNKNOWN
Classifier: Environment :: Web Environment
Classifier: Framework :: Plone
Classifier: Programming Language :: Python
Classifier: Programming Language :: Python :: 2.7
Classifier: Operating System :: OS Independent
Classifier: License :: OSI Approved :: GNU General Public License v2 (GPLv2)
